{"Code":"998655","Name":"Paradise Town Villa Belhamra","Description":"The villa has unlimited fiber internet at 100 MBPS and 1 TON spare water tank and pressure booster against water cuts.\nTHE PRICE DOES NOT INCLUDE ELECTRICITY, GAS AND WATER CONSUMPTION WHICH IS CHARGED ACCORDING TO THE METERS. The staff will take the meters together with you upon your arrival and departure and you will need to pay IN CASH for the you used.\nGarden of Tolerance and Troy Aqua \u0026 Dolphinarium, Paradise TownVilla Belhamra is a villa providing free WiFi and 24-hour security system. Along with the private villa\u0027s unique facilities, guests can access to common facilities such as semi-olympic outdoor pool, indoor fitness center, tennis courts and children playground.The villa has a flat-screen TV with satellite channels, a well-equipped kitchen with a dishwasher and an oven, and a bathroom with a bath. Free private parking is available at Paradise Town Villa Belhamra.","Category":"VILLA","Chain":"","AccommodationType":"Hotel","Destination":"Antalya","District":"Belek","Address":{"Street":"Alan Cad. 124 Sok. Paradise Town Villas, 0","PostCode":"07525","City":"SERIK","CountryCode":"TR"},"Facilities":[{"Name":"Total number of rooms","IsFree":true},{"Name":"hotel","IsFree":true},{"Name":"Wheelchair-accessible","IsFree":true},{"Name":"Car park","IsFree":true},{"Name":"Garage","IsFree":true},{"Name":"24-hour reception","IsFree":true},{"Name":"Check-in hour","IsFree":true},{"Name":"Check-out hour","IsFree":true},{"Name":"Wired Internet","IsFree":true},{"Name":"Wi-fi","IsFree":true},{"Name":"Secure parking","IsFree":true},{"Name":"Launderette","IsFree":true},{"Name":"Garden","IsFree":true},{"Name":"Terrace","IsFree":true},{"Name":"Sun terrace","IsFree":true},{"Name":"Oven","IsFree":true},{"Name":"Dining area","IsFree":true},{"Name":"Grill/BBQ","IsFree":true},{"Name":"Private pool","IsFree":true},{"Name":"Electric kettle","IsFree":true},{"Name":"No hen/stag or any other parties allowed","IsFree":true}],"Images":[{"Description":"Room","ThumbnailUrl":"https://photos.hotelbeds.com/giata/99/998655/998655a_hb_ro_005.jpeg","OriginalUrl":"https://photos.hotelbeds.com/giata/original/99/998655/998655a_hb_ro_005.jpeg"},{"Description":"Room","ThumbnailUrl":"https://photos.hotelbeds.com/giata/99/998655/998655a_hb_ro_004.jpeg","OriginalUrl":"https://photos.hotelbeds.com/giata/original/99/998655/998655a_hb_ro_004.jpeg"},{"Description":"Room","ThumbnailUrl":"https://photos.hotelbeds.com/giata/99/998655/998655a_hb_ro_007.jpeg","OriginalUrl":"https://photos.hotelbeds.com/giata/original/99/998655/998655a_hb_ro_007.jpeg"},{"Description":"Room","ThumbnailUrl":"https://photos.hotelbeds.com/giata/99/998655/998655a_hb_ro_006.jpeg","OriginalUrl":"https://photos.hotelbeds.com/giata/original/99/998655/998655a_hb_ro_006.jpeg"},{"Description":"General view","ThumbnailUrl":"https://photos.hotelbeds.com/giata/99/998655/998655a_hb_a_010.jpg","OriginalUrl":"https://photos.hotelbeds.com/giata/original/99/998655/998655a_hb_a_010.jpg"},{"Description":"General view","ThumbnailUrl":"https://photos.hotelbeds.com/giata/99/998655/998655a_hb_a_011.jpg","OriginalUrl":"https://photos.hotelbeds.com/giata/original/99/998655/998655a_hb_a_011.jpg"},{"Description":"General view","ThumbnailUrl":"https://photos.hotelbeds.com/giata/99/998655/998655a_hb_a_012.jpg","OriginalUrl":"https://photos.hotelbeds.com/giata/original/99/998655/998655a_hb_a_012.jpg"},{"Description":"General view","ThumbnailUrl":"https://photos.hotelbeds.com/giata/99/998655/998655a_hb_a_006.jpg","OriginalUrl":"https://photos.hotelbeds.com/giata/original/99/998655/998655a_hb_a_006.jpg"},{"Description":"Lobby","ThumbnailUrl":"https://photos.hotelbeds.com/giata/99/998655/998655a_hb_l_001.jpeg","OriginalUrl":"https://photos.hotelbeds.com/giata/original/99/998655/998655a_hb_l_001.jpeg"},{"Description":"General view","ThumbnailUrl":"https://photos.hotelbeds.com/giata/99/998655/998655a_hb_a_005.jpg","OriginalUrl":"https://photos.hotelbeds.com/giata/original/99/998655/998655a_hb_a_005.jpg"},{"Description":"General view","ThumbnailUrl":"https://photos.hotelbeds.com/giata/99/998655/998655a_hb_a_008.jpg","OriginalUrl":"https://photos.hotelbeds.com/giata/original/99/998655/998655a_hb_a_008.jpg"},{"Description":"General view","ThumbnailUrl":"https://photos.hotelbeds.com/giata/99/998655/998655a_hb_a_007.jpg","OriginalUrl":"https://photos.hotelbeds.com/giata/original/99/998655/998655a_hb_a_007.jpg"},{"Description":"Lobby","ThumbnailUrl":"https://photos.hotelbeds.com/giata/99/998655/998655a_hb_l_002.jpeg","OriginalUrl":"https://photos.hotelbeds.com/giata/original/99/998655/998655a_hb_l_002.jpeg"},{"Description":"General view","ThumbnailUrl":"https://photos.hotelbeds.com/giata/99/998655/998655a_hb_a_009.jpg","OriginalUrl":"https://photos.hotelbeds.com/giata/original/99/998655/998655a_hb_a_009.jpg"},{"Description":"General view","ThumbnailUrl":"https://photos.hotelbeds.com/giata/99/998655/998655a_hb_a_001.jpeg","OriginalUrl":"https://photos.hotelbeds.com/giata/original/99/998655/998655a_hb_a_001.jpeg"},{"Description":"General view","ThumbnailUrl":"https://photos.hotelbeds.com/giata/99/998655/998655a_hb_a_004.jpg","OriginalUrl":"https://photos.hotelbeds.com/giata/original/99/998655/998655a_hb_a_004.jpg"},{"Description":"General view","ThumbnailUrl":"https://photos.hotelbeds.com/giata/99/998655/998655a_hb_a_003.jpg","OriginalUrl":"https://photos.hotelbeds.com/giata/original/99/998655/998655a_hb_a_003.jpg"},{"Description":"Room","ThumbnailUrl":"https://photos.hotelbeds.com/giata/99/998655/998655a_hb_ro_017.jpeg","OriginalUrl":"https://photos.hotelbeds.com/giata/original/99/998655/998655a_hb_ro_017.jpeg"},{"Description":"Room","ThumbnailUrl":"https://photos.hotelbeds.com/giata/99/998655/998655a_hb_ro_016.jpeg","OriginalUrl":"https://photos.hotelbeds.com/giata/original/99/998655/998655a_hb_ro_016.jpeg"},{"Description":"Room","ThumbnailUrl":"https://photos.hotelbeds.com/giata/99/998655/998655a_hb_ro_015.jpeg","OriginalUrl":"https://photos.hotelbeds.com/giata/original/99/998655/998655a_hb_ro_015.jpeg"},{"Description":"Room","ThumbnailUrl":"https://photos.hotelbeds.com/giata/99/998655/998655a_hb_ro_014.jpeg","OriginalUrl":"https://photos.hotelbeds.com/giata/original/99/998655/998655a_hb_ro_014.jpeg"},{"Description":"Room","ThumbnailUrl":"https://photos.hotelbeds.com/giata/99/998655/998655a_hb_ro_013.jpeg","OriginalUrl":"https://photos.hotelbeds.com/giata/original/99/998655/998655a_hb_ro_013.jpeg"},{"Description":"Room","ThumbnailUrl":"https://photos.hotelbeds.com/giata/99/998655/998655a_hb_ro_012.jpeg","OriginalUrl":"https://photos.hotelbeds.com/giata/original/99/998655/998655a_hb_ro_012.jpeg"},{"Description":"Room","ThumbnailUrl":"https://photos.hotelbeds.com/giata/99/998655/998655a_hb_ro_011.jpeg","OriginalUrl":"https://photos.hotelbeds.com/giata/original/99/998655/998655a_hb_ro_011.jpeg"},{"Description":"Room","ThumbnailUrl":"https://photos.hotelbeds.com/giata/99/998655/998655a_hb_ro_010.jpeg","OriginalUrl":"https://photos.hotelbeds.com/giata/original/99/998655/998655a_hb_ro_010.jpeg"},{"Description":"Room","ThumbnailUrl":"https://photos.hotelbeds.com/giata/99/998655/998655a_hb_ro_009.jpeg","OriginalUrl":"https://photos.hotelbeds.com/giata/original/99/998655/998655a_hb_ro_009.jpeg"},{"Description":"Room","ThumbnailUrl":"https://photos.hotelbeds.com/giata/99/998655/998655a_hb_ro_008.jpeg","OriginalUrl":"https://photos.hotelbeds.com/giata/original/99/998655/998655a_hb_ro_008.jpeg"}],"Phones":[{"PhoneType":"PHONEBOOKING","PhoneNumber":"\u002B905322194900"},{"PhoneType":"PHONEHOTEL","PhoneNumber":"\u002B905322194900"}]}